seqlog/__init__.py
seqlog/consumer.py
seqlog/feature_flags.py
seqlog/structured_logging.py
seqlog-0.4.2.dist-info/AUTHORS.rst
seqlog-0.4.2.dist-info/LICENSE
seqlog-0.4.2.dist-info/METADATA
seqlog-0.4.2.dist-info/WHEEL
seqlog-0.4.2.dist-info/top_level.txt
seqlog-0.4.2.dist-info/RECORD
