Metadata-Version: 2.1
Name: seqlog
Version: 0.4.2
Summary: SeqLog enables logging from Python to Seq.
Home-page: https://github.com/tintoy/seqlog
Author: Adam Friedman
Author-email: tintoy@tintoy.io
License: MIT license
Keywords: seqlog
Classifier: Development Status :: 4 - Beta
Classifier: Intended Audience :: Developers
Classifier: License :: OSI Approved :: MIT License
Classifier: Natural Language :: English
Classifier: Programming Language :: Python :: 3.6
Classifier: Programming Language :: Python :: 3.8
Classifier: Programming Language :: Python :: 3.9
Classifier: Programming Language :: Python :: 3.10
Classifier: Programming Language :: Python :: 3.11
License-File: LICENSE
License-File: AUTHORS.rst
Requires-Dist: python-dateutil (>=2.5.3)
Requires-Dist: requests (>=2.10.0)
Requires-Dist: PyYAML (>=3.11)
